[
  {
    "title": "Doraemon Anime_L2",
    "link_thumb": "https://live.staticflickr.com/65535/51787822699_65a8baf3b6_o.gif",
    "id_album": "405661392",
    "total": 16,
    "size_max_detail_page": 1,
    "list_detail": [
      {
        "index_page": 0,
        "link_page": "https://github.com/lmbstudiocontact/mb5_dt_alb_0/raw/main/14132021_dta_405661392_index_0.json"
      }
    ]
  },
  {
    "title": "Other",
    "link_thumb": "https://live.staticflickr.com/65535/51787848694_ee7b7f98d4_o.gif",
    "id_album": "76517104",
    "total": 62,
    "size_max_detail_page": 2,
    "list_detail": [
      {
        "index_page": 0,
        "link_page": "https://github.com/lmbstudiocontact/mb5_dt_alb_0/raw/main/14132021_dta_76517104_index_0.json"
      },
      {
        "index_page": 1,
        "link_page": "https://github.com/lmbstudiocontact/mb5_dt_alb_0/raw/main/14132021_dta_76517104_index_1.json"
      }
    ]
  },
  {
    "title": "Spider Man Cartoon_L5",
    "link_thumb": "https://live.staticflickr.com/65535/51787256366_89333576aa_o.gif",
    "id_album": "1735002395",
    "total": 16,
    "size_max_detail_page": 1,
    "list_detail": [
      {
        "index_page": 0,
        "link_page": "https://github.com/lmbstudiocontact/mb5_dt_alb_0/raw/main/14132021_dta_1735002395_index_0.json"
      }
    ]
  },
  {
    "title": "Tiger_L7",
    "link_thumb": "https://live.staticflickr.com/65535/51787536163_6b76da330c_o.gif",
    "id_album": "2111354123",
    "total": 2,
    "size_max_detail_page": 1,
    "list_detail": [
      {
        "index_page": 0,
        "link_page": "https://github.com/lmbstudiocontact/mb5_dt_alb_0/raw/main/14132021_dta_2111354123_index_0.json"
      }
    ]
  },
  {
    "title": "Rio 2_L1",
    "link_thumb": "https://live.staticflickr.com/65535/51787918524_20f9c25f4b_o.gif",
    "id_album": "-1210862918",
    "total": 17,
    "size_max_detail_page": 1,
    "list_detail": [
      {
        "index_page": 0,
        "link_page": "https://github.com/lmbstudiocontact/mb5_dt_alb_0/raw/main/14132021_dta_-1210862918_index_0.json"
      }
    ]
  },
  {
    "title": "Couple Art_L7",
    "link_thumb": "https://live.staticflickr.com/65535/51787190046_cf4889beb9_o.gif",
    "id_album": "1239230759",
    "total": 48,
    "size_max_detail_page": 1,
    "list_detail": [
      {
        "index_page": 0,
        "link_page": "https://github.com/lmbstudiocontact/mb5_dt_alb_0/raw/main/14132021_dta_1239230759_index_0.json"
      }
    ]
  },
  {
    "title": "Death Note Anime_L4",
    "link_thumb": "https://live.staticflickr.com/65535/51787821219_600b609ef0_o.gif",
    "id_album": "-374116171",
    "total": 8,
    "size_max_detail_page": 1,
    "list_detail": [
      {
        "index_page": 0,
        "link_page": "https://github.com/lmbstudiocontact/mb5_dt_alb_0/raw/main/14132021_dta_-374116171_index_0.json"
      }
    ]
  },
  {
    "title": "Seven deadly sins Anime_L1",
    "link_thumb": "https://live.staticflickr.com/65535/51787525508_b0909b85ea_o.gif",
    "id_album": "1802210937",
    "total": 43,
    "size_max_detail_page": 1,
    "list_detail": [
      {
        "index_page": 0,
        "link_page": "https://github.com/lmbstudiocontact/mb5_dt_alb_0/raw/main/14132021_dta_1802210937_index_0.json"
      }
    ]
  },
  {
    "title": "Lilo & Stitch Cartoon_L3",
    "link_thumb": "https://live.staticflickr.com/65535/51787515518_3f51f3848c_o.gif",
    "id_album": "685543661",
    "total": 30,
    "size_max_detail_page": 1,
    "list_detail": [
      {
        "index_page": 0,
        "link_page": "https://github.com/lmbstudiocontact/mb5_dt_alb_0/raw/main/14132021_dta_685543661_index_0.json"
      }
    ]
  },
  {
    "title": "Lion_L6",
    "link_thumb": "https://live.staticflickr.com/65535/51788116155_16e414766f_o.gif",
    "id_album": "1842745421",
    "total": 3,
    "size_max_detail_page": 1,
    "list_detail": [
      {
        "index_page": 0,
        "link_page": "https://github.com/lmbstudiocontact/mb5_dt_alb_0/raw/main/14132021_dta_1842745421_index_0.json"
      }
    ]
  },
  {
    "title": "Halloween Ghost Witch_L2",
    "link_thumb": "https://live.staticflickr.com/65535/51786438107_00be8bcbca_o.gif",
    "id_album": "1746571234",
    "total": 49,
    "size_max_detail_page": 1,
    "list_detail": [
      {
        "index_page": 0,
        "link_page": "https://github.com/lmbstudiocontact/mb5_dt_alb_0/raw/main/14132021_dta_1746571234_index_0.json"
      }
    ]
  },
  {
    "title": "Donald Duck Cartoon_L5",
    "link_thumb": "https://live.staticflickr.com/65535/51788075335_72894e4a5f_o.gif",
    "id_album": "-1917621481",
    "total": 4,
    "size_max_detail_page": 1,
    "list_detail": [
      {
        "index_page": 0,
        "link_page": "https://github.com/lmbstudiocontact/mb5_dt_alb_0/raw/main/14132021_dta_-1917621481_index_0.json"
      }
    ]
  },
  {
    "title": "Simpsons Cartoon",
    "link_thumb": "https://live.staticflickr.com/65535/51787224896_0c6a314e25_o.gif",
    "id_album": "-1732735896",
    "total": 4,
    "size_max_detail_page": 1,
    "list_detail": [
      {
        "index_page": 0,
        "link_page": "https://github.com/lmbstudiocontact/mb5_dt_alb_0/raw/main/14132021_dta_-1732735896_index_0.json"
      }
    ]
  },
  {
    "title": "Sheep_L6",
    "link_thumb": "https://live.staticflickr.com/65535/51788145735_1463f06049_o.gif",
    "id_album": "-576277778",
    "total": 2,
    "size_max_detail_page": 1,
    "list_detail": [
      {
        "index_page": 0,
        "link_page": "https://github.com/lmbstudiocontact/mb5_dt_alb_0/raw/main/14132021_dta_-576277778_index_0.json"
      }
    ]
  },
  {
    "title": "Peko_L7",
    "link_thumb": "https://live.staticflickr.com/65535/51787267866_ce77d39168_o.gif",
    "id_album": "979611953",
    "total": 5,
    "size_max_detail_page": 1,
    "list_detail": [
      {
        "index_page": 0,
        "link_page": "https://github.com/lmbstudiocontact/mb5_dt_alb_0/raw/main/14132021_dta_979611953_index_0.json"
      }
    ]
  },
  {
    "title": "Dau Mam_L7",
    "link_thumb": "https://live.staticflickr.com/65535/51787453913_9bb8144acd_o.gif",
    "id_album": "-1324347431",
    "total": 101,
    "size_max_detail_page": 3,
    "list_detail": [
      {
        "index_page": 0,
        "link_page": "https://github.com/lmbstudiocontact/mb5_dt_alb_0/raw/main/14132021_dta_-1324347431_index_0.json"
      },
      {
        "index_page": 1,
        "link_page": "https://github.com/lmbstudiocontact/mb5_dt_alb_0/raw/main/14132021_dta_-1324347431_index_1.json"
      },
      {
        "index_page": 2,
        "link_page": "https://github.com/lmbstudiocontact/mb5_dt_alb_0/raw/main/14132021_dta_-1324347431_index_2.json"
      }
    ]
  },
  {
    "title": "Music_L1",
    "link_thumb": "https://live.staticflickr.com/65535/51787279041_e5d05ea45d_o.gif",
    "id_album": "908522975",
    "total": 24,
    "size_max_detail_page": 1,
    "list_detail": [
      {
        "index_page": 0,
        "link_page": "https://github.com/lmbstudiocontact/mb5_dt_alb_0/raw/main/14132021_dta_908522975_index_0.json"
      }
    ]
  },
  {
    "title": "Boss Baby Cartoon_L5",
    "link_thumb": "https://live.staticflickr.com/65535/51787218111_84c02d2114_o.gif",
    "id_album": "158762705",
    "total": 16,
    "size_max_detail_page": 1,
    "list_detail": [
      {
        "index_page": 0,
        "link_page": "https://github.com/lmbstudiocontact/mb5_dt_alb_0/raw/main/14132021_dta_158762705_index_0.json"
      }
    ]
  },
  {
    "title": "Boku No Hero Academia Anime_L1",
    "link_thumb": "https://live.staticflickr.com/65535/51787218316_5d9d334ae1_o.gif",
    "id_album": "197312539",
    "total": 19,
    "size_max_detail_page": 1,
    "list_detail": [
      {
        "index_page": 0,
        "link_page": "https://github.com/lmbstudiocontact/mb5_dt_alb_0/raw/main/14132021_dta_197312539_index_0.json"
      }
    ]
  },
  {
    "title": "Doraemon Anime_L3",
    "link_thumb": "https://live.staticflickr.com/65535/51787821134_c7156cb91d_o.gif",
    "id_album": "405661393",
    "total": 16,
    "size_max_detail_page": 1,
    "list_detail": [
      {
        "index_page": 0,
        "link_page": "https://github.com/lmbstudiocontact/mb5_dt_alb_0/raw/main/14132021_dta_405661393_index_0.json"
      }
    ]
  },
  {
    "title": "Unicorn_L6",
    "link_thumb": "https://live.staticflickr.com/65535/51786442487_c61c01cb89_o.gif",
    "id_album": "-1508743535",
    "total": 18,
    "size_max_detail_page": 1,
    "list_detail": [
      {
        "index_page": 0,
        "link_page": "https://github.com/lmbstudiocontact/mb5_dt_alb_0/raw/main/14132021_dta_-1508743535_index_0.json"
      }
    ]
  },
  {
    "title": "Star War_L5",
    "link_thumb": "https://live.staticflickr.com/65535/51787872559_01d40c9e74_o.gif",
    "id_album": "-1637191762",
    "total": 2,
    "size_max_detail_page": 1,
    "list_detail": [
      {
        "index_page": 0,
        "link_page": "https://github.com/lmbstudiocontact/mb5_dt_alb_0/raw/main/14132021_dta_-1637191762_index_0.json"
      }
    ]
  },
  {
    "title": "Girl_L6",
    "link_thumb": "https://live.staticflickr.com/65535/51787234951_10b5e679b7_o.gif",
    "id_album": "1702905293",
    "total": 194,
    "size_max_detail_page": 4,
    "list_detail": [
      {
        "index_page": 0,
        "link_page": "https://github.com/lmbstudiocontact/mb5_dt_alb_0/raw/main/14132021_dta_1702905293_index_0.json"
      },
      {
        "index_page": 1,
        "link_page": "https://github.com/lmbstudiocontact/mb5_dt_alb_0/raw/main/14132021_dta_1702905293_index_1.json"
      },
      {
        "index_page": 2,
        "link_page": "https://github.com/lmbstudiocontact/mb5_dt_alb_0/raw/main/14132021_dta_1702905293_index_2.json"
      },
      {
        "index_page": 3,
        "link_page": "https://github.com/lmbstudiocontact/mb5_dt_alb_0/raw/main/14132021_dta_1702905293_index_3.json"
      }
    ]
  },
  {
    "title": "Seven deadly sins Anime_L2",
    "link_thumb": "https://live.staticflickr.com/65535/51788133450_91c9fb5216_o.gif",
    "id_album": "1802210938",
    "total": 43,
    "size_max_detail_page": 1,
    "list_detail": [
      {
        "index_page": 0,
        "link_page": "https://github.com/lmbstudiocontact/mb5_dt_alb_0/raw/main/14132021_dta_1802210938_index_0.json"
      }
    ]
  },
  {
    "title": "Horror Art_L2",
    "link_thumb": "https://live.staticflickr.com/65535/51787257531_bf512b12f6_o.gif",
    "id_album": "529377272",
    "total": 41,
    "size_max_detail_page": 1,
    "list_detail": [
      {
        "index_page": 0,
        "link_page": "https://github.com/lmbstudiocontact/mb5_dt_alb_0/raw/main/14132021_dta_529377272_index_0.json"
      }
    ]
  },
  {
    "title": "Detective Conan_L3",
    "link_thumb": "https://live.staticflickr.com/65535/51787816909_0b80d3445d_o.gif",
    "id_album": "-1285383390",
    "total": 16,
    "size_max_detail_page": 1,
    "list_detail": [
      {
        "index_page": 0,
        "link_page": "https://github.com/lmbstudiocontact/mb5_dt_alb_0/raw/main/14132021_dta_-1285383390_index_0.json"
      }
    ]
  },
  {
    "title": "Disney Cartoon_L5",
    "link_thumb": "https://live.staticflickr.com/65535/51788088485_6ceac4eb57_o.gif",
    "id_album": "-779586266",
    "total": 54,
    "size_max_detail_page": 2,
    "list_detail": [
      {
        "index_page": 0,
        "link_page": "https://github.com/lmbstudiocontact/mb5_dt_alb_0/raw/main/14132021_dta_-779586266_index_0.json"
      },
      {
        "index_page": 1,
        "link_page": "https://github.com/lmbstudiocontact/mb5_dt_alb_0/raw/main/14132021_dta_-779586266_index_1.json"
      }
    ]
  },
  {
    "title": "Moana Cartoon_L2",
    "link_thumb": "https://live.staticflickr.com/65535/51787918024_2c35aa11c0_o.gif",
    "id_album": "-2101867515",
    "total": 13,
    "size_max_detail_page": 1,
    "list_detail": [
      {
        "index_page": 0,
        "link_page": "https://github.com/lmbstudiocontact/mb5_dt_alb_0/raw/main/14132021_dta_-2101867515_index_0.json"
      }
    ]
  },
  {
    "title": "Music_L4",
    "link_thumb": "https://live.staticflickr.com/65535/51787256851_d470e97fe2_o.gif",
    "id_album": "908522978",
    "total": 24,
    "size_max_detail_page": 1,
    "list_detail": [
      {
        "index_page": 0,
        "link_page": "https://github.com/lmbstudiocontact/mb5_dt_alb_0/raw/main/14132021_dta_908522978_index_0.json"
      }
    ]
  },
  {
    "title": "Raccoons_L4",
    "link_thumb": "https://live.staticflickr.com/65535/51787523723_d9b94511d7_o.gif",
    "id_album": "1998705267",
    "total": 20,
    "size_max_detail_page": 1,
    "list_detail": [
      {
        "index_page": 0,
        "link_page": "https://github.com/lmbstudiocontact/mb5_dt_alb_0/raw/main/14132021_dta_1998705267_index_0.json"
      }
    ]
  },
  {
    "title": "Totoro_L6",
    "link_thumb": "https://live.staticflickr.com/65535/51786461702_176b1d28b2_o.gif",
    "id_album": "1833828886",
    "total": 41,
    "size_max_detail_page": 1,
    "list_detail": [
      {
        "index_page": 0,
        "link_page": "https://github.com/lmbstudiocontact/mb5_dt_alb_0/raw/main/14132021_dta_1833828886_index_0.json"
      }
    ]
  },
  {
    "title": "Animal Art_L3",
    "link_thumb": "https://live.staticflickr.com/65535/51787832149_46e328bd41_o.gif",
    "id_album": "97007463",
    "total": 7,
    "size_max_detail_page": 1,
    "list_detail": [
      {
        "index_page": 0,
        "link_page": "https://github.com/lmbstudiocontact/mb5_dt_alb_0/raw/main/14132021_dta_97007463_index_0.json"
      }
    ]
  },
  {
    "title": "Doraemon Anime_L5",
    "link_thumb": "https://live.staticflickr.com/65535/51786375182_cf6901e7f8_o.gif",
    "id_album": "405661395",
    "total": 16,
    "size_max_detail_page": 1,
    "list_detail": [
      {
        "index_page": 0,
        "link_page": "https://github.com/lmbstudiocontact/mb5_dt_alb_0/raw/main/14132021_dta_405661395_index_0.json"
      }
    ]
  },
  {
    "title": "Monkey_L7",
    "link_thumb": "https://live.staticflickr.com/65535/51788160730_a7f2141678_o.gif",
    "id_album": "444828983",
    "total": 2,
    "size_max_detail_page": 1,
    "list_detail": [
      {
        "index_page": 0,
        "link_page": "https://github.com/lmbstudiocontact/mb5_dt_alb_0/raw/main/14132021_dta_444828983_index_0.json"
      }
    ]
  },
  {
    "title": "Dragon Ball Anime_L4",
    "link_thumb": "https://live.staticflickr.com/65535/51787844729_91e1c3e66b_o.gif",
    "id_album": "1464725223",
    "total": 60,
    "size_max_detail_page": 2,
    "list_detail": [
      {
        "index_page": 0,
        "link_page": "https://github.com/lmbstudiocontact/mb5_dt_alb_0/raw/main/14132021_dta_1464725223_index_0.json"
      },
      {
        "index_page": 1,
        "link_page": "https://github.com/lmbstudiocontact/mb5_dt_alb_0/raw/main/14132021_dta_1464725223_index_1.json"
      }
    ]
  },
  {
    "title": "Halloween Ghost Witch_L5",
    "link_thumb": "https://live.staticflickr.com/65535/51786416352_949fa26b74_o.gif",
    "id_album": "1746571237",
    "total": 49,
    "size_max_detail_page": 1,
    "list_detail": [
      {
        "index_page": 0,
        "link_page": "https://github.com/lmbstudiocontact/mb5_dt_alb_0/raw/main/14132021_dta_1746571237_index_0.json"
      }
    ]
  },
  {
    "title": "Naruto Anime_L2",
    "link_thumb": "https://live.staticflickr.com/65535/51786458632_f393d9c039_o.gif",
    "id_album": "1894397984",
    "total": 37,
    "size_max_detail_page": 1,
    "list_detail": [
      {
        "index_page": 0,
        "link_page": "https://github.com/lmbstudiocontact/mb5_dt_alb_0/raw/main/14132021_dta_1894397984_index_0.json"
      }
    ]
  },
  {
    "title": "One Piece Anime_L2",
    "link_thumb": "https://live.staticflickr.com/65535/51787271761_a01eed82f2_o.gif",
    "id_album": "1351456605",
    "total": 135,
    "size_max_detail_page": 3,
    "list_detail": [
      {
        "index_page": 0,
        "link_page": "https://github.com/lmbstudiocontact/mb5_dt_alb_0/raw/main/14132021_dta_1351456605_index_0.json"
      },
      {
        "index_page": 1,
        "link_page": "https://github.com/lmbstudiocontact/mb5_dt_alb_0/raw/main/14132021_dta_1351456605_index_1.json"
      },
      {
        "index_page": 2,
        "link_page": "https://github.com/lmbstudiocontact/mb5_dt_alb_0/raw/main/14132021_dta_1351456605_index_2.json"
      }
    ]
  },
  {
    "title": "Buddhist Terms_L1",
    "link_thumb": "https://live.staticflickr.com/65535/51787203691_b0f95a86f8_o.gif",
    "id_album": "518853928",
    "total": 13,
    "size_max_detail_page": 1,
    "list_detail": [
      {
        "index_page": 0,
        "link_page": "https://github.com/lmbstudiocontact/mb5_dt_alb_0/raw/main/14132021_dta_518853928_index_0.json"
      }
    ]
  },
  {
    "title": "Shiv_L2",
    "link_thumb": "https://live.staticflickr.com/65535/51787885559_9a167281e8_o.gif",
    "id_album": "-568595357",
    "total": 32,
    "size_max_detail_page": 1,
    "list_detail": [
      {
        "index_page": 0,
        "link_page": "https://github.com/lmbstudiocontact/mb5_dt_alb_0/raw/main/14132021_dta_-568595357_index_0.json"
      }
    ]
  },
  {
    "title": "Donald Duck Cartoon_L2",
    "link_thumb": "https://live.staticflickr.com/65535/51787828149_589f6acf55_o.gif",
    "id_album": "-1917621484",
    "total": 4,
    "size_max_detail_page": 1,
    "list_detail": [
      {
        "index_page": 0,
        "link_page": "https://github.com/lmbstudiocontact/mb5_dt_alb_0/raw/main/14132021_dta_-1917621484_index_0.json"
      }
    ]
  },
  {
    "title": "Raccoons_L2",
    "link_thumb": "https://live.staticflickr.com/65535/51787909324_622a6eebbe_o.gif",
    "id_album": "1998705265",
    "total": 20,
    "size_max_detail_page": 1,
    "list_detail": [
      {
        "index_page": 0,
        "link_page": "https://github.com/lmbstudiocontact/mb5_dt_alb_0/raw/main/14132021_dta_1998705265_index_0.json"
      }
    ]
  },
  {
    "title": "Disney Cartoon_L2",
    "link_thumb": "https://live.staticflickr.com/65535/51788083220_ca341c11da_o.gif",
    "id_album": "-779586269",
    "total": 54,
    "size_max_detail_page": 2,
    "list_detail": [
      {
        "index_page": 0,
        "link_page": "https://github.com/lmbstudiocontact/mb5_dt_alb_0/raw/main/14132021_dta_-779586269_index_0.json"
      },
      {
        "index_page": 1,
        "link_page": "https://github.com/lmbstudiocontact/mb5_dt_alb_0/raw/main/14132021_dta_-779586269_index_1.json"
      }
    ]
  },
  {
    "title": "One Piece Anime_L1",
    "link_thumb": "https://live.staticflickr.com/65535/51788162630_9678a8a784_o.gif",
    "id_album": "1351456604",
    "total": 135,
    "size_max_detail_page": 3,
    "list_detail": [
      {
        "index_page": 0,
        "link_page": "https://github.com/lmbstudiocontact/mb5_dt_alb_0/raw/main/14132021_dta_1351456604_index_0.json"
      },
      {
        "index_page": 1,
        "link_page": "https://github.com/lmbstudiocontact/mb5_dt_alb_0/raw/main/14132021_dta_1351456604_index_1.json"
      },
      {
        "index_page": 2,
        "link_page": "https://github.com/lmbstudiocontact/mb5_dt_alb_0/raw/main/14132021_dta_1351456604_index_2.json"
      }
    ]
  },
  {
    "title": "Angry Birds_L1",
    "link_thumb": "https://live.staticflickr.com/65535/51786382957_442781f870_o.gif",
    "id_album": "2112729289",
    "total": 26,
    "size_max_detail_page": 1,
    "list_detail": [
      {
        "index_page": 0,
        "link_page": "https://github.com/lmbstudiocontact/mb5_dt_alb_0/raw/main/14132021_dta_2112729289_index_0.json"
      }
    ]
  },
  {
    "title": "Donald Duck Cartoon_L1",
    "link_thumb": "https://live.staticflickr.com/65535/51787206001_823073a1e8_o.gif",
    "id_album": "-1917621485",
    "total": 4,
    "size_max_detail_page": 1,
    "list_detail": [
      {
        "index_page": 0,
        "link_page": "https://github.com/lmbstudiocontact/mb5_dt_alb_0/raw/main/14132021_dta_-1917621485_index_0.json"
      }
    ]
  },
  {
    "title": "Moana Cartoon_L4",
    "link_thumb": "https://live.staticflickr.com/65535/51787537938_9da15c4896_o.gif",
    "id_album": "-2101867513",
    "total": 13,
    "size_max_detail_page": 1,
    "list_detail": [
      {
        "index_page": 0,
        "link_page": "https://github.com/lmbstudiocontact/mb5_dt_alb_0/raw/main/14132021_dta_-2101867513_index_0.json"
      }
    ]
  },
  {
    "title": "Mickey Cartoon_L4",
    "link_thumb": "https://live.staticflickr.com/65535/51788120090_665ac5b1ae_o.gif",
    "id_album": "1680949825",
    "total": 22,
    "size_max_detail_page": 1,
    "list_detail": [
      {
        "index_page": 0,
        "link_page": "https://github.com/lmbstudiocontact/mb5_dt_alb_0/raw/main/14132021_dta_1680949825_index_0.json"
      }
    ]
  },
  {
    "title": "Detective Conan_L5",
    "link_thumb": "https://live.staticflickr.com/65535/51788092150_ec27c0fe84_o.gif",
    "id_album": "-1285383388",
    "total": 16,
    "size_max_detail_page": 1,
    "list_detail": [
      {
        "index_page": 0,
        "link_page": "https://github.com/lmbstudiocontact/mb5_dt_alb_0/raw/main/14132021_dta_-1285383388_index_0.json"
      }
    ]
  },
  {
    "title": "Joker Harley Quinn_L2",
    "link_thumb": "https://live.staticflickr.com/65535/51787895324_14e17f2b13_o.gif",
    "id_album": "-2022175636",
    "total": 24,
    "size_max_detail_page": 1,
    "list_detail": [
      {
        "index_page": 0,
        "link_page": "https://github.com/lmbstudiocontact/mb5_dt_alb_0/raw/main/14132021_dta_-2022175636_index_0.json"
      }
    ]
  }
]